vnpy_evo/__init__.py
vnpy_evo/chart/__init__.py
vnpy_evo/event/__init__.py
vnpy_evo/rest/__init__.py
vnpy_evo/rest/rest_client.py
vnpy_evo/rpc/__init__.py
vnpy_evo/trader/__init__.py
vnpy_evo/trader/app.py
vnpy_evo/trader/constant.py
vnpy_evo/trader/converter.py
vnpy_evo/trader/database.py
vnpy_evo/trader/datafeed.py
vnpy_evo/trader/engine.py
vnpy_evo/trader/event.py
vnpy_evo/trader/gateway.py
vnpy_evo/trader/object.py
vnpy_evo/trader/optimize.py
vnpy_evo/trader/setting.py
vnpy_evo/trader/utility.py
vnpy_evo/trader/ui/__init__.py
vnpy_evo/trader/ui/mainwindow.py
vnpy_evo/trader/ui/monitor.py
vnpy_evo/trader/ui/qt.py
vnpy_evo/trader/ui/widget.py
vnpy_evo/trader/ui/ico/__init__.py
vnpy_evo/trader/ui/ico/veighna.ico
vnpy_evo/websocket/__init__.py
vnpy_evo/websocket/websocket_client.py
vnpy_evo-0.3.2.dist-info/LICENSE
vnpy_evo-0.3.2.dist-info/METADATA
vnpy_evo-0.3.2.dist-info/WHEEL
vnpy_evo-0.3.2.dist-info/top_level.txt
vnpy_evo-0.3.2.dist-info/RECORD
