Metadata-Version: 2.1
Name: vnpy-evo
Version: 0.3.2
Summary: Core module for using VeighNa project in crypto markets.
Home-page: https://www.github.com/veighna-global
Author: VeighNa Global
Author-email: veighna@hotmail.com
License: MIT
Project-URL: Documentation, https://github.com/veighna-global/vnpy_evo
Keywords: quant,quantitative,investment,trading,algotrading,crypto,btc
Classifier: Development Status :: 4 - Beta
Classifier: Operating System :: Microsoft :: Windows
Classifier: Operating System :: POSIX :: Linux
Classifier: Operating System :: MacOS
Classifier: Programming Language :: Python :: 3
Classifier: Programming Language :: Python :: 3.10
Classifier: Programming Language :: Python :: 3.11
Classifier: Programming Language :: Python :: 3.12
Classifier: Topic :: Office/Business :: Financial :: Investment
Classifier: Programming Language :: Python :: Implementation :: CPython
Classifier: License :: OSI Approved :: MIT License
Classifier: Natural Language :: English
License-File: LICENSE
Requires-Dist: numpy ==1.26.4
Requires-Dist: vnpy
Requires-Dist: importlib-metadata
Requires-Dist: PySide6-Fluent-Widgets
Requires-Dist: requests >=2.32.3
Requires-Dist: websocket-client >=1.8.0
Requires-Dist: loguru >=0.7.2
